facebook_simple_scraper/__init__.py
facebook_simple_scraper/credentials_ring.py
facebook_simple_scraper/default_values.py
facebook_simple_scraper/dependency_builder.py
facebook_simple_scraper/entities.py
facebook_simple_scraper/error_dict.py
facebook_simple_scraper/scraper.py
facebook_simple_scraper/stop_conditions.py
facebook_simple_scraper/details/__init__.py
facebook_simple_scraper/details/extractor.py
facebook_simple_scraper/details/repository.py
facebook_simple_scraper/login/__init__.py
facebook_simple_scraper/login/domain.py
facebook_simple_scraper/login/login.py
facebook_simple_scraper/login/params.py
facebook_simple_scraper/login/session_storage.py
facebook_simple_scraper/login/urls.py
facebook_simple_scraper/login/user_info.py
facebook_simple_scraper/posts/__init__.py
facebook_simple_scraper/posts/summary_extractor.py
facebook_simple_scraper/posts/summary_repository.py
facebook_simple_scraper/requester/__init__.py
facebook_simple_scraper/requester/headers.py
facebook_simple_scraper/requester/requester.py
facebook_simple_scraper-0.1.14.dist-info/LICENCE
facebook_simple_scraper-0.1.14.dist-info/METADATA
facebook_simple_scraper-0.1.14.dist-info/WHEEL
facebook_simple_scraper-0.1.14.dist-info/top_level.txt
facebook_simple_scraper-0.1.14.dist-info/RECORD
